sql_faker/__init__.py
sql_faker/cache_dict.py
sql_faker/datatype.py
sql_faker/db_utils.py
sql_faker/examples.py
sql_faker/faker.py
sql_faker/mapping.py
sql_faker/sql_faker.py
sql_faker/times.py
sql_faker/values.py
sql_faker/asserts/__init__.py
sql_faker/asserts/asserts.py
sql_faker/random_data/__init__.py
sql_faker/random_data/address_random.py
sql_faker/random_data/age_random.py
sql_faker/random_data/email_random.py
sql_faker/random_data/id_random.py
sql_faker/random_data/phone_random.py
sql_faker/random_data/random_abstract.py
sql_faker/random_data/sex_random.py
sql_faker/random_data/time_random.py
sql_faker/random_data/username_random.py
sql_faker/sql/__init__.py
sql_faker-1.1.7.data/data/README.md
sql_faker-1.1.7.dist-info/LICENSE
sql_faker-1.1.7.dist-info/METADATA
sql_faker-1.1.7.dist-info/WHEEL
sql_faker-1.1.7.dist-info/top_level.txt
sql_faker-1.1.7.dist-info/RECORD
