Metadata-Version: 2.1
Name: sql-faker
Version: 1.1.7
Summary: A lightweight SQL data creator
Home-page: https://github.com/lkmc2/python-sql-faker
Author: lkmc2
Author-email: lkmc2@163.com
License: UNKNOWN
Platform: all
Classifier: Programming Language :: Python
Classifier: Programming Language :: Python :: Implementation
Classifier: Programming Language :: Python :: 2.7
Classifier: Operating System :: OS Independent
Requires-Dist: DBUtils (>=1.3)
Requires-Dist: pymysql (>=0.9.2)
